math_assistant/__init__.py
math_assistant/__main__.py
math_assistant/cli.py
math_assistant/config.py
math_assistant/exceptions.py
math_assistant/formatters.py
math_assistant/image_processor.py
math_assistant/math_assistant.py
math_assistant/version.py
tests/__init__.py
tests/test_image_processor.py
tests/test_math_assistant.py
math_assistant_cli-0.1.1.dist-info/LICENSE
math_assistant_cli-0.1.1.dist-info/METADATA
math_assistant_cli-0.1.1.dist-info/WHEEL
math_assistant_cli-0.1.1.dist-info/entry_points.txt
math_assistant_cli-0.1.1.dist-info/top_level.txt
math_assistant_cli-0.1.1.dist-info/RECORD
