Metadata-Version: 2.1
Name: math-assistant-cli
Version: 0.1.1
Summary: AI-powered math problem solver and tutor
Home-page: https://github.com/LucasRimfrost/math-assistant-cli
Author: Lucas Rimfrost
Author-email: lucas.rimfrost@gmail.com
License: MIT
Keywords: mathematics education ai tutor claude anthropic
Classifier: Development Status :: 3 - Alpha
Classifier: Intended Audience :: Education
Classifier: License :: OSI Approved :: MIT License
Classifier: Programming Language :: Python :: 3.8
Classifier: Programming Language :: Python :: 3.9
Classifier: Programming Language :: Python :: 3.10
Classifier: Topic :: Education
Classifier: Topic :: Scientific/Engineering :: Mathematics
Requires-Python: >=3.8
License-File: LICENSE
Requires-Dist: anthropic >=0.5.0
Requires-Dist: Pillow >=9.0.0
Requires-Dist: rich >=10.0.0
Requires-Dist: click >=8.0.0
